{
  "tag": "中國軍力",
  "date": "2026-02-22",
  "title": "中國艦隊部署現況",
  "desc": "對台射程涵蓋各型東風飛彈旅部署位置與裝備",
  "content": "##055型驅逐艦\n112個垂發單元，海紅旗-9B/C防空導彈、鷹擊-18反艦導彈、長劍-10巡航導彈等；\n##052D型驅逐艦\n64單元，海紅旗-9B/C防空導彈、鷹擊-18反艦導彈、魚-8反潛火箭助飛魚雷\n##054A型護衛艦\n32單元，紅旗-16中程防空導彈、魚-8反潛魚雷，數量龐大（40+艘）\n\n典型的中國海軍編隊，由 1艘055型驅逐艦、2艘052D型驅逐艦、4艘054A型護衛艦組成\n368單元，防空導彈（HQ-9/HQ-16）：約 50% → ~184枚；反艦導彈（鷹擊-18等）：約 30% → ~110枚；反潛武器（魚-8火箭助飛魚雷）：約 15% → ~55枚；對地/巡航導彈（長劍-10等）：約 5% → ~19枚，具備 多層防空、反艦飽和攻擊、有限對地打擊。",
  "table": {
    "headers": [
      "單位名稱",
      "駐地",
      "類型",
      "裝備"
    ],
    "rows": [
      [
        "遼寧號航母戰鬥群",
        "山東青島",
        "航母戰鬥群",
        "遼寧號/1, 055型/2, 052D型/4"
      ],
      [
        "山東號航母戰鬥群",
        "海南三亞",
        "航母戰鬥群",
        "山東號/1, 055型/2, 052D型/4"
      ],
      [
        "東海艦隊第1驅逐艦支隊",
        "浙江舟山",
        "驅逐艦群",
        "055型/4, 052D型/8"
      ],
      [
        "東海艦隊第2驅逐艦支隊",
        "浙江舟山",
        "驅逐艦群",
        "052D型/5, 054A型/8"
      ],
      [
        "南海艦隊驅護支隊",
        "廣東湛江",
        "驅護混編",
        "052D型/5, 054A型/8"
      ],
      [
        "東海艦隊潛艦支隊",
        "浙江舟山",
        "核潛艦群",
        "093型/6"
      ],
      [
        "南海艦隊潛艦支隊",
        "海南三亞",
        "常規潛艦群",
        "041型/10"
      ],
      [
        "第1兩棲編隊",
        "廣東湛江",
        "登陸艦群",
        "075型/2, 071型/4"
      ],
      [
        "第2兩棲編隊",
        "上海",
        "登陸艦群",
        "075型/1, 071型/4"
      ]
    ]
  }
}